README.md
setup.cfg
setup.py
mpl_format/__init__.py
mpl_format/compound_types.py
mpl_format/literals.py
mpl_format/settings.py
mpl_format.egg-info/PKG-INFO
mpl_format.egg-info/SOURCES.txt
mpl_format.egg-info/dependency_links.txt
mpl_format.egg-info/requires.txt
mpl_format.egg-info/top_level.txt
mpl_format/animation/__init__.py
mpl_format/animation/rate.py
mpl_format/animation/type_animations.py
mpl_format/animation/animators/__init__.py
mpl_format/animation/animators/axes_animator.py
mpl_format/animation/kwarg_animations/__init__.py
mpl_format/animation/kwarg_animations/color_animation.py
mpl_format/animation/kwarg_animations/float_animation.py
mpl_format/animation/shapes/__init__.py
mpl_format/animation/shapes/arc_animation.py
mpl_format/animation/shapes/arrow_animation.py
mpl_format/animation/shapes/base.py
mpl_format/animation/shapes/circle_animation.py
mpl_format/animation/shapes/ellipse_animation.py
mpl_format/animation/shapes/line_animation.py
mpl_format/animation/shapes/rectangle_animation.py
mpl_format/animation/shapes/regular_polygon_animation.py
mpl_format/animation/shapes/text_animation.py
mpl_format/animation/shapes/wedge_animation.py
mpl_format/axes/__init__.py
mpl_format/axes/axes_formatter.py
mpl_format/axes/axes_formatter_array.py
mpl_format/axes/axis_formatter.py
mpl_format/axes/axis_formatter_array.py
mpl_format/axes/axis_utils.py
mpl_format/axes/ticks_formatter.py
mpl_format/colors/__init__.py
mpl_format/colors/color_maps.py
mpl_format/colors/office.py
mpl_format/enums/__init__.py
mpl_format/enums/arrow_style.py
mpl_format/enums/box_style.py
mpl_format/enums/cap_style.py
mpl_format/enums/connection_style.py
mpl_format/enums/draw_style.py
mpl_format/enums/font_size.py
mpl_format/enums/font_stretch.py
mpl_format/enums/font_style.py
mpl_format/enums/font_variant.py
mpl_format/enums/font_weight.py
mpl_format/enums/join_style.py
mpl_format/enums/line_style.py
mpl_format/enums/mappings.py
mpl_format/enums/marker_style.py
mpl_format/figures/__init__.py
mpl_format/figures/figure_formatter.py
mpl_format/figures/figure_utils.py
mpl_format/legend/__init__.py
mpl_format/legend/legend_formatter.py
