Metadata-Version: 1.1
Name: mpl-format
Version: 0.319
Summary: Library for easier formatting of matplotlib plots written in a functional style.
Home-page: https://github.com/vahndi/mpl-format
Author: Vahndi Minah
Author-email: UNKNOWN
License: MIT
Keywords: matplotlib
Platform: UNKNOWN
Classifier: Development Status :: 3 - Alpha
Classifier: Intended Audience :: Developers
Classifier: License :: OSI Approved :: MIT License
Classifier: Programming Language :: Python :: 3
